argparcel/__init__.py
argparcel/docstrings.py
argparcel/py.typed
argparcel-0.0.8.dist-info/WHEEL
argparcel-0.0.8.dist-info/METADATA
argparcel-0.0.8.dist-info/RECORD
