Metadata-Version: 2.4
Name: argparcel
Version: 0.0.8
Summary: Parse command-line arguments into a dataclass
Author: Tom Gillam
Author-email: Tom Gillam <tpgillam@googlemail.com>
License-Expression: MIT
Classifier: Development Status :: 3 - Alpha
Classifier: Intended Audience :: Developers
Classifier: Natural Language :: English
Classifier: Programming Language :: Python :: 3
Classifier: Programming Language :: Python :: 3.12
Classifier: Programming Language :: Python :: 3.13
Classifier: Programming Language :: Python :: 3.14
Requires-Python: >=3.12
Project-URL: Homepage, https://github.com/tpgillam/argparcel
